[
  {
    "Candidate Name": "Hari Teja Patnala",
    "Contact Number": "+919392329691",
    "Email Address": "patnalahariteja@gmail.com",
    "Location": "Phagwara",
    "Current Headline": null,
    "Links": {
      "linkedin": null,
      "github": "github.com/hariteja-01",
      "portfolio": "leetcode.com/u/hariteja01",
      "other": []
    },
    "overall_confidence": 0.434
  },
  {
    "Candidate Name": "Jane M. Doe",
    "Contact Number": "+14155552671",
    "Email Address": "jane.doe@email.com",
    "Location": "San Francisco",
    "Current Headline": "Senior Machine Learning Engineer",
    "Links": {
      "linkedin": null,
      "github": "github.com/janedoe",
      "portfolio": null,
      "other": []
    },
    "overall_confidence": 0.85
  },
  {
    "Candidate Name": "John Smith",
    "Contact Number": "+442079460958",
    "Email Address": "john.smith@example.com",
    "Location": "London",
    "Current Headline": "Full Stack Developer",
    "Links": null,
    "overall_confidence": 0.77
  },
  {
    "Candidate Name": "Alex Rivera",
    "Contact Number": "+16505558834",
    "Email Address": "alex.rivera@techmail.com",
    "Location": "Austin",
    "Current Headline": "Data Engineer",
    "Links": null,
    "overall_confidence": 0.54
  },
  {
    "Candidate Name": "Torvalds",
    "Contact Number": null,
    "Email Address": null,
    "Location": null,
    "Current Headline": null,
    "Links": {
      "linkedin": null,
      "github": "https://github.com/torvalds",
      "portfolio": null,
      "other": []
    },
    "overall_confidence": 0.12
  },
  {
    "Candidate Name": "Octocat",
    "Contact Number": null,
    "Email Address": null,
    "Location": null,
    "Current Headline": null,
    "Links": {
      "linkedin": null,
      "github": "https://github.com/octocat",
      "portfolio": null,
      "other": []
    },
    "overall_confidence": 0.12
  }
]